darkhistory/__init__.py
darkhistory/config.py
darkhistory/main.py
darkhistory/physics.py
darkhistory/utilities.py
darkhistory/electrons/Electrons_v1.ipynb
darkhistory/electrons/H_1s-2p_excite_table.csv
darkhistory/electrons/He_1s-2p_excite_table.csv
darkhistory/electrons/Module_Es.ipynb
darkhistory/electrons/Peart_Hep_ionization.csv
darkhistory/electrons/Shah_H_ionization.csv
darkhistory/electrons/Shah_He_ionization.csv
darkhistory/electrons/__init__.py
darkhistory/electrons/elec_cooling.py
darkhistory/electrons/ion_heat_transfer.ipynb
darkhistory/electrons/ion_heat_transfer_simplified.ipynb
darkhistory/electrons/positronium.py
darkhistory/electrons/xsecs.py
darkhistory/electrons/ics/BE_integrals.py
darkhistory/electrons/ics/__init__.py
darkhistory/electrons/ics/engloss_diff_terms.py
darkhistory/electrons/ics/ics_cooling.py
darkhistory/electrons/ics/ics_engloss_spectrum.py
darkhistory/electrons/ics/ics_spectrum.py
darkhistory/electrons/ics/nonrel_diff_terms.py
darkhistory/history/__init__.py
darkhistory/history/histools.py
darkhistory/history/reionization.py
darkhistory/history/tla.py
darkhistory/low_energy/__init__.py
darkhistory/low_energy/lowE_deposition.py
darkhistory/low_energy/lowE_electrons.py
darkhistory/low_energy/lowE_photons.py
darkhistory/low_energy/results-10.2ev-xH-xHe_e-10-yp024.dat
darkhistory/low_energy/results-100.0ev-xH-xHe_e-10-yp024.dat
darkhistory/low_energy/results-13.6ev-xH-xHe_e-10-yp024.dat
darkhistory/low_energy/results-14.0ev-xH-xHe_e-10-yp024.dat
darkhistory/low_energy/results-30.0ev-xH-xHe_e-10-yp024.dat
darkhistory/low_energy/results-300.0ev-xH-xHe_e-10-yp024.dat
darkhistory/low_energy/results-3000.0ev-xH-xHe_e-10-yp024.dat
darkhistory/low_energy/results-60.0ev-xH-xHe_e-10-yp024.dat
darkhistory/nntf/__init__.py
darkhistory/nntf/load.py
darkhistory/nntf/nntf.py
darkhistory/nntf/tfbase.py
darkhistory/nntf/utils.py
darkhistory/numpy_groupies/__init__.py
darkhistory/numpy_groupies/aggregate.py
darkhistory/spec/__init__.py
darkhistory-1.1.2.20250616.dist-info/licenses/LICENSE
darkhistory-1.1.2.20250616.dist-info/METADATA
darkhistory-1.1.2.20250616.dist-info/WHEEL
darkhistory-1.1.2.20250616.dist-info/top_level.txt
darkhistory-1.1.2.20250616.dist-info/RECORD
