Metadata-Version: 2.4
Name: darkhistory
Version: 1.1.2.20250616
Summary: Base DarkHistory. Used in DM21cm. NN transfer functions available.
Project-URL: Homepage, https://github.com/hongwanliu/DarkHistory
Requires-Python: >=3.10
License-File: LICENSE
Requires-Dist: astropy>=5.3
Requires-Dist: h5py
Requires-Dist: matplotlib
Requires-Dist: numpy>=1.25.2
Requires-Dist: pytest
Requires-Dist: scipy>=1.11.2
Requires-Dist: tqdm
Dynamic: license-file
